spychronous.py
non_daemonic_process/__init__.py
non_daemonic_process/non_daemonic_processing.py
spychronous-1.0.post4.dist-info/LICENSE.txt
spychronous-1.0.post4.dist-info/METADATA
spychronous-1.0.post4.dist-info/WHEEL
spychronous-1.0.post4.dist-info/top_level.txt
spychronous-1.0.post4.dist-info/RECORD
