Metadata-Version: 2.1
Name: spychronous
Version: 1.0.post4
Summary: A simple synchronous job runner for parallel processing tasks in Python.
Home-page: https://github.com/scparedes/spychronous
Author: Santiago C Paredes
Author-email: santiago.paredes2012@gmail.com
License: MIT
Download-URL: https://github.com/scparedes/spychronous/releases/download/1.0.post4/spychronous-1.0.post4.tar.gz
Keywords: multiprocessing,multiprocess,multi,process,synchronous,job,runner,simple
Platform: UNKNOWN
Classifier: Development Status :: 5 - Production/Stable
Classifier: Intended Audience :: Developers
Classifier: Topic :: Software Development :: Build Tools
Classifier: License :: OSI Approved :: MIT License
Classifier: Programming Language :: Python :: 2
Classifier: Programming Language :: Python :: 2.6
Classifier: Programming Language :: Python :: 2.7
